costyl/.DS_Store
costyl/__init__.py
costyl/analysers/__init__.py
costyl/analysers/layout.py
costyl/analysers/lexical.py
costyl/tools.py
costyl/vectorizer/__init__.py
costyl/vectorizer/__vectorizer.py
costyl-0.3.0.dist-info/METADATA
costyl-0.3.0.dist-info/WHEEL
costyl-0.3.0.dist-info/RECORD
