Metadata-Version: 2.1
Name: costyl
Version: 0.3.0
Summary: Costyl is a python library to facilitate source code authorship attribution via stylometric analysis powered by machine learning.
Author: Jbernardiss
Author-email: joaobernardiss@gmail.com
Requires-Python: >=3.9,<4.0
Classifier: Programming Language :: Python :: 3
Classifier: Programming Language :: Python :: 3.9
Classifier: Programming Language :: Python :: 3.10
Classifier: Programming Language :: Python :: 3.11
Classifier: Programming Language :: Python :: 3.12
Requires-Dist: numpy (==1.26.4)
Requires-Dist: scikit-learn (==1.2.2)
Requires-Dist: scipy (==1.12.0)
